algorithms/__init__.py
algorithms/mcts_connect4.py
algorithms/mcts_tictactoe.py
algorithms/minimax_connect4.py
algorithms/minimax_tictactoe.py
algorithms/pruning_connect4.py
algorithms/pruning_tictactoe.py
games/__init__.py
games/connect4.py
games/tic_tac_toe.py
py_adverse_search-1.0.7.dist-info/LICENSE.txt
py_adverse_search-1.0.7.dist-info/METADATA
py_adverse_search-1.0.7.dist-info/WHEEL
py_adverse_search-1.0.7.dist-info/top_level.txt
py_adverse_search-1.0.7.dist-info/RECORD
